seffaflik2/__init__.py
seffaflik2/seffaflik2.py
seffaflik2-0.1.0.dist-info/METADATA
seffaflik2-0.1.0.dist-info/WHEEL
seffaflik2-0.1.0.dist-info/top_level.txt
seffaflik2-0.1.0.dist-info/RECORD
