Metadata-Version: 2.1
Name: seffaflik2
Version: 0.1.0
Summary: EPIAS Transparency Platform 2.0 Unofficial Python Library
Home-page: https://github.com/berkomeratay/seffaflik2
Author: Berk Ömer Atay
Author-email: <berkomeratay@gmail.com>
Keywords: python,epias,seffaflik,epias transparency platform,transparency,epiaş şeffaflık platformu
Requires-Dist: requests
Requires-Dist: pandas
Requires-Dist: numpy
